LICENSE
README.md
setup.py
MedSimilarity.egg-info/PKG-INFO
MedSimilarity.egg-info/SOURCES.txt
MedSimilarity.egg-info/dependency_links.txt
MedSimilarity.egg-info/requires.txt
MedSimilarity.egg-info/top_level.txt
medsimilarity/__init__.py
medsimilarity/medsimilarity.py
medsimilarity/utils.py