Metadata-Version: 2.1
Name: MedSimilarity
Version: 1.0.0
Summary: MedSimilarity is an open source Python to compare 2D medical images.
Home-page: https://github.com/UM2ii/MedSimilarity
Author: Pranav Kulkarni
Author-email: pranavkop@live.com
License: Apache License
Classifier: Intended Audience :: Developers
Classifier: Intended Audience :: Education
Classifier: Intended Audience :: Science/Research
Classifier: License :: OSI Approved :: Apache Software License
Classifier: Development Status :: 5 - Production/Stable
Classifier: Programming Language :: Python :: 3.6
Classifier: Topic :: Scientific/Engineering :: Artificial Intelligence
Requires-Python: >=3.6
License-File: LICENSE
